pippin_naco/__init__.py
pippin_naco/__main__.py
pippin_naco/auxiliary_functions.py
pippin_naco/beam_fitting.py
pippin_naco/figures.py
pippin_naco/pippin_naco.py
pippin_naco/sky_subtraction.py
pippin_naco-0.1.1.dist-info/LICENSE
pippin_naco-0.1.1.dist-info/METADATA
pippin_naco-0.1.1.dist-info/WHEEL
pippin_naco-0.1.1.dist-info/entry_points.txt
pippin_naco-0.1.1.dist-info/top_level.txt
pippin_naco-0.1.1.dist-info/RECORD
