Metadata-Version: 2.1
Name: pippin-naco
Version: 0.1.1
Summary: A comprehensive PDI pipeline for NACO data (PIPPIN)
Home-page: https://pippin-naco.readthedocs.io
Author: Sam de Regt
Author-email: regt@strw.leidenuniv.nl
License: MIT
Classifier: Development Status :: 3 - Alpha
Classifier: Intended Audience :: Science/Research
Classifier: License :: OSI Approved :: MIT License
Classifier: Operating System :: POSIX :: Linux
Classifier: Programming Language :: Python :: 3.10
Classifier: Topic :: Scientific/Engineering :: Astronomy
Requires-Python: >=3.10
License-File: LICENSE
Requires-Dist: numpy (>=1.21.4)
Requires-Dist: matplotlib (>=3.5.1)
Requires-Dist: scipy (>=1.7.3)
Requires-Dist: astropy (>=5.0)
Requires-Dist: astroquery (>=0.4.3)
Requires-Dist: tqdm (>=4.60.0)
Requires-Dist: pathlib (>=1.0.1)
